tablewriter.py
tablewriter-0.0.1.5.dist-info/DESCRIPTION.rst
tablewriter-0.0.1.5.dist-info/METADATA
tablewriter-0.0.1.5.dist-info/RECORD
tablewriter-0.0.1.5.dist-info/WHEEL
tablewriter-0.0.1.5.dist-info/metadata.json
tablewriter-0.0.1.5.dist-info/top_level.txt
