Metadata-Version: 2.0
Name: tablewriter
Version: 0.0.1.5
Summary: latex table generator
Home-page: https://gitlab.com/cottephi/latextablegenerator
Author: cottephi
Author-email: cottephi@gmail.com
License: UNKNOWN
Platform: UNKNOWN
Classifier: Programming Language :: Python :: 3.7
Classifier: Operating System :: Unix
